morgana/.DS_Store
morgana/__init__.py
morgana/__main__.py
morgana/.ipynb_checkpoints/Quantify-checkpoint.ipynb
morgana/DatasetTools/.DS_Store
morgana/DatasetTools/__init__.py
morgana/DatasetTools/arrangefluodata.py
morgana/DatasetTools/arrangemorphodata.py
morgana/DatasetTools/io.py
morgana/DatasetTools/__pycache__/__init__.cpython-36.pyc
morgana/DatasetTools/__pycache__/__init__.cpython-37.pyc
morgana/DatasetTools/__pycache__/__init__.cpython-38.pyc
morgana/DatasetTools/__pycache__/__init__.cpython-39.pyc
morgana/DatasetTools/__pycache__/arrangefluodata.cpython-36.pyc
morgana/DatasetTools/__pycache__/arrangefluodata.cpython-37.pyc
morgana/DatasetTools/__pycache__/arrangefluodata.cpython-38.pyc
morgana/DatasetTools/__pycache__/arrangefluodata.cpython-39.pyc
morgana/DatasetTools/__pycache__/arrangegroupdata.cpython-37.pyc
morgana/DatasetTools/__pycache__/arrangemorphodata.cpython-36.pyc
morgana/DatasetTools/__pycache__/arrangemorphodata.cpython-37.pyc
morgana/DatasetTools/__pycache__/arrangemorphodata.cpython-38.pyc
morgana/DatasetTools/__pycache__/arrangemorphodata.cpython-39.pyc
morgana/DatasetTools/__pycache__/io.cpython-36.pyc
morgana/DatasetTools/__pycache__/io.cpython-37.pyc
morgana/DatasetTools/__pycache__/io.cpython-38.pyc
morgana/DatasetTools/__pycache__/io.cpython-39.pyc
morgana/DatasetTools/fluorescence/__init__.py
morgana/DatasetTools/fluorescence/computefluorescence.py
morgana/DatasetTools/fluorescence/io.py
morgana/DatasetTools/fluorescence/__pycache__/__init__.cpython-36.pyc
morgana/DatasetTools/fluorescence/__pycache__/__init__.cpython-37.pyc
morgana/DatasetTools/fluorescence/__pycache__/__init__.cpython-38.pyc
morgana/DatasetTools/fluorescence/__pycache__/__init__.cpython-39.pyc
morgana/DatasetTools/fluorescence/__pycache__/computefluorescence.cpython-36.pyc
morgana/DatasetTools/fluorescence/__pycache__/computefluorescence.cpython-37.pyc
morgana/DatasetTools/fluorescence/__pycache__/computefluorescence.cpython-38.pyc
morgana-0.1.1.dist-info/LICENSE
morgana-0.1.1.dist-info/METADATA
morgana-0.1.1.dist-info/WHEEL
morgana-0.1.1.dist-info/top_level.txt
morgana-0.1.1.dist-info/RECORD
