Metadata-Version: 2.1
Name: morgana
Version: 0.1.1
Summary: A machine learning tool to segment organoids.
Home-page: https://github.com/LabTrivedi/MOrgAna
Author: Nicola Gritti
Author-email: gritti@embl.es
License: UNKNOWN
Platform: UNKNOWN
Classifier: Programming Language :: Python :: 3
Classifier: License :: OSI Approved :: MIT License
Classifier: Operating System :: OS Independent
Requires-Python: >=3.6
Requires-Dist: matplotlib
Requires-Dist: numpy (>=1.20)
Requires-Dist: scikit-image (>=0.18)
Requires-Dist: pandas (>=1.2)
Requires-Dist: joblib (>=1.0)
Requires-Dist: scikit-learn (>=0.24)
Requires-Dist: scipy (>=1.6)
Requires-Dist: tqdm (>=4.60)
